{"schema":6,"addons":[{"id":"langpack-en-US@firefox.mozilla.org","icons":{"32":"https://addons.mozilla.org/static-server/img/addon-icons/default-32.2b26add4b394.png","64":"https://addons.mozilla.org/static-server/img/addon-icons/default-64.d144b50f2bb8.png","128":"https://addons.mozilla.org/static-server/img/addon-icons/default-128.452018499894.png"},"name":"English (US) Language Pack","version":"111.0buildid20230306.162820","sourceURI":"https://addons.mozilla.org/firefox/downloads/file/4080034/english_us_language_pack-111.0buildid20230306.162820.xpi","homepageURL":null,"supportURL":null,"description":"The en-US language pack for Firefox.","fullDescription":null,"weeklyDownloads":2239,"type":"locale","creator":{"name":"Mozilla Firefox","url":"https://addons.mozilla.org/en-US/firefox/user/4757633/"},"developers":[],"screenshots":[],"contributionURL":"","averageRating":4.1765,"reviewCount":119,"reviewURL":"https://addons.mozilla.org/en-US/firefox/addon/english-us-language-pack/reviews/","updateDate":1678132673000}]}